firebase_user/__init__.py
firebase_user/fb_user.py
firebase_user-0.0.21.dist-info/LICENSE
firebase_user-0.0.21.dist-info/METADATA
firebase_user-0.0.21.dist-info/WHEEL
firebase_user-0.0.21.dist-info/top_level.txt
firebase_user-0.0.21.dist-info/RECORD
