Metadata-Version: 2.1
Name: firebase_user
Version: 0.0.21
Summary: Client interface for the firebase REST API.
Home-page: https://github.com/B4PT0R/firebase_user
Author: Baptiste Ferrand
Author-email: bferrand.maths@gmail.com
Classifier: Programming Language :: Python :: 3
Classifier: License :: OSI Approved :: MIT License
Classifier: Operating System :: OS Independent
Requires-Python: >=3.6
License-File: LICENSE
Requires-Dist: objdict-bf
Requires-Dist: requests
